adel_lite/__init__.py
adel_lite/cli.py
adel_lite/constraints.py
adel_lite/export.py
adel_lite/map.py
adel_lite/meta.py
adel_lite/profile.py
adel_lite/sample.py
adel_lite/schema.py
adel_lite/utils.py
adel_lite/visualize.py
adel_lite-0.1.1.dist-info/licenses/LICENCE
tests/__init__.py
tests/conftest.py
tests/test_constraints.py
tests/test_map.py
tests/test_profile.py
tests/test_schema.py
tests/test_utils.py
adel_lite-0.1.1.dist-info/METADATA
adel_lite-0.1.1.dist-info/WHEEL
adel_lite-0.1.1.dist-info/entry_points.txt
adel_lite-0.1.1.dist-info/top_level.txt
adel_lite-0.1.1.dist-info/RECORD
