Metadata-Version: 2.4
Name: adel-lite
Version: 0.1.1
Summary: Automated Data Elements Linking - Lite
Home-page: https://github.com/Parthnuwal7/adel-lite.git
Author: Parth Nuwal
Author-email: Parth Nuwal <parthnuwal7@gmail.com>
License: MIT
Keywords: data,schema,profiling,pandas,automation
Classifier: Development Status :: 3 - Alpha
Classifier: Intended Audience :: Developers
Classifier: License :: OSI Approved :: MIT License
Classifier: Programming Language :: Python :: 3
Requires-Python: >=3.8
License-File: LICENCE
Requires-Dist: pandas>=1.3.0
Requires-Dist: numpy>=1.21.0
Requires-Dist: pyyaml>=6.0
Requires-Dist: networkx>=2.6
Requires-Dist: matplotlib>=3.5.0
Requires-Dist: graphviz>=0.20.0
Requires-Dist: fuzzywuzzy>=0.18.0
Requires-Dist: python-levenshtein>=0.12.0
Provides-Extra: dev
Requires-Dist: pytest>=7.0.0; extra == "dev"
Requires-Dist: pytest-cov>=4.0.0; extra == "dev"
Requires-Dist: black>=22.0.0; extra == "dev"
Requires-Dist: flake8>=5.0.0; extra == "dev"
Requires-Dist: mypy>=0.991; extra == "dev"
Dynamic: author
Dynamic: home-page
Dynamic: license-file
Dynamic: requires-python
